inm_rspace/__init__.py
inm_rspace/core.py
inm_rspace/pyrightconfig.json
inm_rspace/workflow.py
inm_rspace-0.4.1.dist-info/LICENSE
inm_rspace-0.4.1.dist-info/METADATA
inm_rspace-0.4.1.dist-info/WHEEL
inm_rspace-0.4.1.dist-info/RECORD
