Metadata-Version: 2.1
Name: inm-rspace
Version: 0.4.1
Summary: Tools for working with the RSpace ELN
Home-page: https://github.com/sintharic/inm-rspace
License: MIT
Keywords: eln,rspace,science,notebook
Author: Christian Müller
Requires-Python: >=3.9
Classifier: License :: OSI Approved :: MIT License
Classifier: Programming Language :: Python :: 3
Classifier: Programming Language :: Python :: 3.9
Classifier: Programming Language :: Python :: 3.10
Classifier: Programming Language :: Python :: 3.11
Classifier: Programming Language :: Python :: 3.12
Requires-Dist: matplotlib
Requires-Dist: numpy (>=1.23)
Requires-Dist: pandas
Requires-Dist: rspace-client
Project-URL: Documentation, https://sintharic.github.io/inm-rspace
Project-URL: Repository, https://github.com/sintharic/inm-rspace
